mindor/__init__.py
mindor/cli/__init__.py
mindor/cli/compose.py
mindor/core/__init__.py
mindor/core/component/__init__.py
mindor/core/component/base.py
mindor/core/component/component.py
mindor/core/component/context.py
mindor/core/component/runtime/__init__.py
mindor/core/component/runtime/process_manager.py
mindor/core/component/runtime/process_worker.py
mindor/core/component/services/__init__.py
mindor/core/component/services/http_client.py
mindor/core/component/services/http_server.py
mindor/core/component/services/image_processor.py
mindor/core/component/services/mcp_client.py
mindor/core/component/services/mcp_server.py
mindor/core/component/services/shell.py
mindor/core/component/services/text_splitter.py
mindor/core/component/services/web_scraper.py
mindor/core/component/services/workflow.py
mindor/core/component/services/datasets/__init__.py
mindor/core/component/services/datasets/datasets.py
mindor/core/component/services/datasets/utils.py
mindor/core/component/services/datasets/providers/__init__.py
mindor/core/component/services/datasets/providers/common.py
mindor/core/component/services/datasets/providers/huggingface.py
mindor/core/component/services/datasets/providers/local.py
mindor/core/component/services/model/__init__.py
mindor/core/component/services/model/model.py
mindor/core/component/services/model/base/__init__.py
mindor/core/component/services/model/base/common.py
mindor/core/component/services/model/base/huggingface.py
mindor/core/component/services/model/base/huggingface_hub.py
mindor/core/component/services/model/base/unsloth.py
mindor/core/component/services/model/tasks/__init__.py
mindor/core/component/services/model/tasks/chat_completion/__init__.py
mindor/core/component/services/model/tasks/chat_completion/huggingface.py
mindor/core/component/services/model/tasks/face_embedding/__init__.py
mindor/core/component/services/model/tasks/face_embedding/common.py
mindor/core/component/services/model/tasks/face_embedding/custom.py
model_compose-0.4.21.dist-info/licenses/LICENSE
model_compose-0.4.21.dist-info/METADATA
model_compose-0.4.21.dist-info/WHEEL
model_compose-0.4.21.dist-info/entry_points.txt
model_compose-0.4.21.dist-info/top_level.txt
model_compose-0.4.21.dist-info/RECORD
