Metadata-Version: 2.4
Name: model-compose
Version: 0.4.21
Summary: model-compose: Declarative AI Workflow Orchestrator
Author-email: Hanyeol Cho <hanyeol.cho@gmail.com>
License-Expression: MIT
Project-URL: Homepage, https://github.com/hanyeol/model-compose
License-File: LICENSE
Requires-Dist: click
Requires-Dist: pyyaml
Requires-Dist: pydantic
Requires-Dist: python-dotenv
Requires-Dist: docker
Requires-Dist: aiohttp
Requires-Dist: requests
Requires-Dist: fastapi
Requires-Dist: uvicorn
Requires-Dist: mcp>=1.10.1
Requires-Dist: ulid
Requires-Dist: gradio
Requires-Dist: Pillow
Requires-Dist: beautifulsoup4
Requires-Dist: lxml
Dynamic: license-file
